approve_api/__init__.py
approve_api/api_client.py
approve_api/configuration.py
approve_api/rest.py
approve_api/api/__init__.py
approve_api/api/approve_api.py
approve_api/models/__init__.py
approve_api/models/error.py
approve_api/models/prompt.py
approve_api/models/prompt_answer.py
approve_api/models/prompt_status.py
test/__init__.py
test/test_approve_api.py
test/test_error.py
test/test_prompt.py
test/test_prompt_answer.py
test/test_prompt_status.py
approve_api-1.0.3.dist-info/METADATA
approve_api-1.0.3.dist-info/WHEEL
approve_api-1.0.3.dist-info/top_level.txt
approve_api-1.0.3.dist-info/RECORD
