Metadata-Version: 2.1
Name: approve-api
Version: 1.0.3
Summary: ApproveAPI
Home-page: UNKNOWN
Author: UNKNOWN
Author-email: dev@approveapi.com
License: UNKNOWN
Keywords: OpenAPI,OpenAPI-Generator,ApproveAPI
Platform: UNKNOWN
Requires-Dist: urllib3 (>=1.15)
Requires-Dist: six (>=1.10)
Requires-Dist: certifi
Requires-Dist: python-dateutil
